weexin/__init__.py
weexin/exceptions.py
weexin/languages.py
weexin/logger.py
weexin/param.py
weexin/uiautomation.py
weexin/wx.py
weexin/msgs/__init__.py
weexin/msgs/attr.py
weexin/msgs/base.py
weexin/msgs/friend.py
weexin/msgs/msg.py
weexin/msgs/self.py
weexin/msgs/type.py
weexin/ui/__init__.py
weexin/ui/base.py
weexin/ui/chatbox.py
weexin/ui/component.py
weexin/ui/main.py
weexin/ui/navigationbox.py
weexin/ui/sessionbox.py
weexin/utils/__init__.py
weexin/utils/tools.py
weexin/utils/win32.py
weexin-1.0.2.dist-info/licenses/LICENSE
weexin-1.0.2.dist-info/METADATA
weexin-1.0.2.dist-info/WHEEL
weexin-1.0.2.dist-info/top_level.txt
weexin-1.0.2.dist-info/RECORD
